{
  "title": "CleanFeed",
  "description": "__MSG_script_desc_cleanfeed",
  "icon": {
    "class_name": "ri-eye-off-line",
    "color": "white",
    "background_color": "#ff567e"
  },
  "help": "https://github.com/AprilSylph/XKit-Rewritten/wiki/Features#cleanfeed",
  "relatedTerms": [ "nsfw" ],
  "preferences": {
    "blockingMode": {
      "label": "Hide media from",
      "type": "select",
      "options": [
        { "value": "smart", "label": "flagged blogs only" },
        { "value": "all", "label": "all blogs" }
      ],
      "default": "smart"
    },
    "localFlagging": {
      "label": "Treat these blogs as flagged (comma-separated)",
      "type": "textarea",
      "default": ""
    }
  }
}
